LICENSE
README.md
setup.py
crypt2file/__init__.py
crypt2file.egg-info/PKG-INFO
crypt2file.egg-info/SOURCES.txt
crypt2file.egg-info/dependency_links.txt
crypt2file.egg-info/entry_points.txt
crypt2file.egg-info/requires.txt
crypt2file.egg-info/top_level.txt