Metadata-Version: 2.1
Name: crypt2file
Version: 1.0.0
Summary: A simple tool to encrypt/decrypt files using a machine-specific key.
Home-page: https://github.com/aloecandy/crypt2file
Author: Kyunghoon
Author-email: aloecandy@gmail.com
License: MIT
Keywords: crypt,file,encrypt,decrypt,security
Classifier: Development Status :: 5 - Production/Stable
Classifier: Intended Audience :: Developers
Classifier: Topic :: Security :: Cryptography
Classifier: License :: OSI Approved :: MIT License
Classifier: Programming Language :: Python :: 3
Classifier: Programming Language :: Python :: 3.7
Classifier: Programming Language :: Python :: 3.8
Classifier: Programming Language :: Python :: 3.9
Classifier: Programming Language :: Python :: 3.10
Classifier: Programming Language :: Python :: 3.11
License-File: LICENSE
